MANIFEST.in
README.rst
requirements.txt
setup.cfg
setup.py
test_requirements.txt
pyhydroquebec/__init__.py
pyhydroquebec/__main__.py
pyhydroquebec/__version__.py
pyhydroquebec/client.py
pyhydroquebec/consts.py
pyhydroquebec/customer.py
pyhydroquebec/error.py
pyhydroquebec/mqtt_daemon.py
pyhydroquebec/outputter.py
pyhydroquebec.egg-info/PKG-INFO
pyhydroquebec.egg-info/SOURCES.txt
pyhydroquebec.egg-info/dependency_links.txt
pyhydroquebec.egg-info/entry_points.txt
pyhydroquebec.egg-info/requires.txt
pyhydroquebec.egg-info/top_level.txt