Metadata-Version: 1.1
Name: pyhydroquebec
Version: 3.0.5
Summary: Get your Hydro Quebec consumption (wwww.hydroquebec.com)
Home-page: http://github.com/titilambert/pyhydroquebec
Author: Thibault Cohen
Author-email: titilambert@gmail.com
License: Apache 2.0
Platform: UNKNOWN
Classifier: Programming Language :: Python :: 3.4
Classifier: Programming Language :: Python :: 3.5
Classifier: Programming Language :: Python :: 3.6
